odoo/addons/sale_stock_picking_invoicing/README.rst
odoo/addons/sale_stock_picking_invoicing/__init__.py
odoo/addons/sale_stock_picking_invoicing/__manifest__.py
odoo/addons/sale_stock_picking_invoicing/demo/sale_order_demo.xml
odoo/addons/sale_stock_picking_invoicing/i18n/it.po
odoo/addons/sale_stock_picking_invoicing/i18n/sale_stock_picking_invoicing.pot
odoo/addons/sale_stock_picking_invoicing/models/__init__.py
odoo/addons/sale_stock_picking_invoicing/models/res_company.py
odoo/addons/sale_stock_picking_invoicing/models/res_config_settings.py
odoo/addons/sale_stock_picking_invoicing/models/sale_order.py
odoo/addons/sale_stock_picking_invoicing/models/sale_order_line.py
odoo/addons/sale_stock_picking_invoicing/models/stock_move.py
odoo/addons/sale_stock_picking_invoicing/models/stock_picking.py
odoo/addons/sale_stock_picking_invoicing/readme/CONFIGURE.rst
odoo/addons/sale_stock_picking_invoicing/readme/CONTRIBUTORS.rst
odoo/addons/sale_stock_picking_invoicing/readme/CREDITS.rst
odoo/addons/sale_stock_picking_invoicing/readme/DESCRIPTION.rst
odoo/addons/sale_stock_picking_invoicing/readme/HISTORY.rst
odoo/addons/sale_stock_picking_invoicing/readme/INSTALL.rst
odoo/addons/sale_stock_picking_invoicing/readme/ROADMAP.rst
odoo/addons/sale_stock_picking_invoicing/readme/USAGE.rst
odoo/addons/sale_stock_picking_invoicing/static/description/icon.png
odoo/addons/sale_stock_picking_invoicing/static/description/index.html
odoo/addons/sale_stock_picking_invoicing/tests/__init__.py
odoo/addons/sale_stock_picking_invoicing/tests/test_sale_stock.py
odoo/addons/sale_stock_picking_invoicing/views/res_company_view.xml
odoo/addons/sale_stock_picking_invoicing/views/res_config_settings_view.xml
odoo/addons/sale_stock_picking_invoicing/wizards/__init__.py
odoo/addons/sale_stock_picking_invoicing/wizards/stock_invoice_onshipping.py
odoo/addons/sale_stock_picking_invoicing/wizards/stock_invoice_onshipping_view.xml
odoo14_addon_sale_stock_picking_invoicing-14.0.1.0.1.dist-info/METADATA
odoo14_addon_sale_stock_picking_invoicing-14.0.1.0.1.dist-info/WHEEL
odoo14_addon_sale_stock_picking_invoicing-14.0.1.0.1.dist-info/top_level.txt
odoo14_addon_sale_stock_picking_invoicing-14.0.1.0.1.dist-info/RECORD
